rpa/__init__.py
utils/__init__.py
utils/bucket.py
utils/logManager.py
yuankongai_test/__init__.py
yuankongai_test/bucket.py
yuankongai_test/logManager.py
yuankongai_test-0.2.dist-info/LICENSE
yuankongai_test-0.2.dist-info/METADATA
yuankongai_test-0.2.dist-info/WHEEL
yuankongai_test-0.2.dist-info/top_level.txt
yuankongai_test-0.2.dist-info/RECORD
