Metadata-Version: 2.1
Name: yuankongai_test
Version: 0.2
Summary: Basic function of YuankongAI
Author: ltq_yuankong
Author-email: 1539365976@qq.com
Classifier: Programming Language :: Python :: 3
Classifier: License :: OSI Approved :: MIT License
Classifier: Operating System :: OS Independent
License-File: LICENSE
